beem_sms/__init__.py
beem_sms/cli.py
beem_sms/client.py
beem_sms/exceptions.py
beem_sms/validators.py
beem_sms_python-1.0.3.dist-info/licenses/LICENSE
tests/__init__.py
tests/conftest.py
tests/test_client.py
tests/test_validators.py
beem_sms_python-1.0.3.dist-info/METADATA
beem_sms_python-1.0.3.dist-info/WHEEL
beem_sms_python-1.0.3.dist-info/entry_points.txt
beem_sms_python-1.0.3.dist-info/top_level.txt
beem_sms_python-1.0.3.dist-info/RECORD
