Metadata-Version: 2.4
Name: beem-sms-python
Version: 1.0.3
Summary: Professional Python SDK for Beem SMS API
Home-page: https://github.com/islandkid-20/beem-sms-python
Author: James Mashaka
Author-email: James Mashaka <j1997ames@gmail.com>
License: MIT License - Copyright (c) 2025 James Mashaka
Project-URL: Homepage, https://github.com/islandkid-20/beem-sms-python
Project-URL: Repository, https://github.com/islandkid-20/beem-sms-python
Keywords: sms,beem,tanzania,messaging,api,sdk
Classifier: Development Status :: 5 - Production/Stable
Classifier: Intended Audience :: Developers
Classifier: Operating System :: OS Independent
Classifier: Programming Language :: Python :: 3
Classifier: Programming Language :: Python :: 3.8
Classifier: Programming Language :: Python :: 3.9
Classifier: Programming Language :: Python :: 3.10
Classifier: Programming Language :: Python :: 3.11
Classifier: Topic :: Communications
Requires-Python: >=3.8
License-File: LICENSE
Requires-Dist: requests>=2.28.0
Requires-Dist: urllib3>=1.26.0
Provides-Extra: dev
Requires-Dist: pytest>=7.0; extra == "dev"
Requires-Dist: pytest-cov>=4.0; extra == "dev"
Requires-Dist: black>=22.0; extra == "dev"
Requires-Dist: isort>=5.12.0; extra == "dev"
Requires-Dist: flake8>=5.0; extra == "dev"
Requires-Dist: mypy>=1.0; extra == "dev"
Requires-Dist: types-requests>=2.28.0; extra == "dev"
Requires-Dist: pre-commit>=2.20; extra == "dev"
Requires-Dist: sphinx>=5.0; extra == "dev"
Requires-Dist: sphinx-rtd-theme>=1.0; extra == "dev"
Requires-Dist: myst-parser>=0.18; extra == "dev"
Dynamic: author
Dynamic: home-page
Dynamic: license-file
Dynamic: requires-python
